flink_rest_client/__init__.py
flink_rest_client/client.py
flink_rest_client/common.py
flink_rest_client/v1/__init__.py
flink_rest_client/v1/client.py
flink_rest_client/v1/jars.py
flink_rest_client/v1/jobmanager.py
flink_rest_client/v1/jobs.py
flink_rest_client/v1/taskmanagers.py
tests/__init__.py
tests/test_client.py
tests/data/__init__.py
tests/data/sample_jars/__init__.py
tests/v1/__init__.py
tests/v1/test_base.py
tests/v1/test_client.py
tests/v1/test_jars.py
tests/v1/test_job_vertex.py
tests/v1/test_job_vertex_subtasks.py
tests/v1/test_jobmanager.py
tests/v1/test_jobs.py
tests/v1/test_taskmanagers.py
flink_rest_client-1.0.8.dist-info/LICENSE
flink_rest_client-1.0.8.dist-info/METADATA
flink_rest_client-1.0.8.dist-info/WHEEL
flink_rest_client-1.0.8.dist-info/entry_points.txt
flink_rest_client-1.0.8.dist-info/top_level.txt
flink_rest_client-1.0.8.dist-info/RECORD
