Metadata-Version: 2.1
Name: flink-rest-client
Version: 1.0.8
Summary: Easy to use Flink REST API client implementation
Home-page: https://github.com/frego-dev/flink-rest-client
Author: Attila Nagy
Author-email: anagy@frego.dev
License: MIT
Platform: UNKNOWN
Requires-Dist: requests
Requires-Dist: importlib-resources
